{"1627774625": [{"crossing": "", "to_cro": "", "from_cro": ""}, {"crossing": "Jasenovac ", "to_cro": "do 30 min.", "from_cro": "do 30 min."}, {"crossing": "Bajakovo ", "to_cro": "do 30 min.", "from_cro": "5 h"}, {"crossing": "Macelj ", "to_cro": "do 30 min.", "from_cro": "3 h"}, {"crossing": "Pasjak ", "to_cro": "3 h", "from_cro": "-"}, {"crossing": "Jurovski Brod ", "to_cro": "-", "from_cro": "do 30 min."}, {"crossing": "Hum na Sutli ", "to_cro": "-", "from_cro": "1 h"}, {"crossing": "Lupinjak ", "to_cro": "-", "from_cro": "do 30 min."}], "1627776002": [{"crossing": "", "to_cro": "", "from_cro": ""}, {"crossing": "Jasenovac ", "to_cro": "do 30 min.", "from_cro": "do 30 min."}, {"crossing": "Bajakovo ", "to_cro": "do 30 min.", "from_cro": "5 h"}, {"crossing": "Macelj ", "to_cro": "-", "from_cro": "3 h"}, {"crossing": "Pasjak ", "to_cro": "3 h", "from_cro": "-"}, {"crossing": "Jurovski Brod ", "to_cro": "-", "from_cro": "do 30 min."}, {"crossing": "Hum na Sutli ", "to_cro": "-", "from_cro": "do 30 min."}, {"crossing": "Lupinjak ", "to_cro": "-", "from_cro": "do 30 min."}], "1627777322": [{"crossing": "", "to_cro": "", "from_cro": ""}, {"crossing": "Jasenovac ", "to_cro": "do 30 min.", "from_cro": "do 30 min."}, {"crossing": "Bajakovo ", "to_cro": "do 30 min.", "from_cro": "5 h"}, {"crossing": "Macelj ", "to_cro": "-", "from_cro": "3 h"}, {"crossing": "Bregana ", "to_cro": "1 h 30 min.", "from_cro": "1 h 30 min."}, {"crossing": "Jurovski Brod ", "to_cro": "-", "from_cro": "do 30 min."}, {"crossing": "Hum na Sutli ", "to_cro": "-", "from_cro": "do 30 min."}, {"crossing": "Lupinjak ", "to_cro": "-", "from_cro": "do 30 min."}], "1627777802": [{"crossing": "", "to_cro": "", "from_cro": ""}, {"crossing": "Jasenovac ", "to_cro": "do 30 min.", "from_cro": "do 30 min."}, {"crossing": "Bajakovo ", "to_cro": "do 30 min.", "from_cro": "5 h"}, {"crossing": "Macelj ", "to_cro": "-", "from_cro": "3 h"}, {"crossing": "Bregana ", "to_cro": "1 h 30 min.", "from_cro": "1 h 30 min."}, {"crossing": "Jurovski Brod ", "to_cro": "-", "from_cro": "do 30 min."}, {"crossing": "Hum na Sutli ", "to_cro": "-", "from_cro": "do 30 min."}, {"crossing": "Lupinjak ", "to_cro": "-", "from_cro": "do 30 min."}], "1627779602": [{"crossing": "", "to_cro": "", "from_cro": ""}, {"crossing": "Jasenovac ", "to_cro": "do 30 min.", "from_cro": "do 30 min."}, {"crossing": "Dubo\u0161evica ", "to_cro": "1 h", "from_cro": "-"}, {"crossing": "Gori\u010dan II ", "to_cro": "do 30 min.", "from_cro": "-"}, {"crossing": "Bajakovo ", "to_cro": "do 30 min.", "from_cro": "5 h"}, {"crossing": "Macelj ", "to_cro": "-", "from_cro": "3 h"}, {"crossing": "Bregana ", "to_cro": "1 h 30 min.", "from_cro": "1 h 30 min."}, {"crossing": "Jurovski Brod ", "to_cro": "-", "from_cro": "do 30 min."}, {"crossing": "Hum na Sutli ", "to_cro": "-", "from_cro": "do 30 min."}, {"crossing": "Lupinjak ", "to_cro": "-", "from_cro": "do 30 min."}], "1627781402": [{"crossing": "", "to_cro": "", "from_cro": ""}, {"crossing": "Jasenovac ", "to_cro": "do 30 min.", "from_cro": "do 30 min."}, {"crossing": "Dubo\u0161evica ", "to_cro": "1 h", "from_cro": "-"}, {"crossing": "Gori\u010dan II ", "to_cro": "do 30 min.", "from_cro": "-"}, {"crossing": "Bajakovo ", "to_cro": "do 30 min.", "from_cro": "5 h"}, {"crossing": "Macelj ", "to_cro": "1 h", "from_cro": "3 h"}, {"crossing": "Bregana ", "to_cro": "1 h 30 min.", "from_cro": "1 h 30 min."}, {"crossing": "Jurovski Brod ", "to_cro": "-", "from_cro": "do 30 min."}, {"crossing": "Hum na Sutli ", "to_cro": "-", "from_cro": "do 30 min."}, {"crossing": "Lupinjak ", "to_cro": "1 h", "from_cro": "do 30 min."}], "1627783203": [{"crossing": "", "to_cro": "", "from_cro": ""}, {"crossing": "Dubo\u0161evica ", "to_cro": "1 h", "from_cro": "-"}, {"crossing": "Gori\u010dan II ", "to_cro": "do 30 min.", "from_cro": "-"}, {"crossing": "Bajakovo ", "to_cro": "do 30 min.", "from_cro": "5 h"}, {"crossing": "Macelj ", "to_cro": "1 h", "from_cro": "3 h"}, {"crossing": "Bregana ", "to_cro": "1 h 30 min.", "from_cro": "1 h 30 min."}, {"crossing": "Jurovski Brod ", "to_cro": "-", "from_cro": "do 30 min."}, {"crossing": "Mursko Sredi\u0161\u0107e ", "to_cro": "1 h", "from_cro": "-"}, {"crossing": "Hum na Sutli ", "to_cro": "-", "from_cro": "do 30 min."}, {"crossing": "Lupinjak ", "to_cro": "1 h", "from_cro": "do 30 min."}], "1627785002": [{"crossing": "", "to_cro": "", "from_cro": ""}, {"crossing": "Dubo\u0161evica ", "to_cro": "1 h", "from_cro": "-"}, {"crossing": "Gori\u010dan II ", "to_cro": "do 30 min.", "from_cro": "-"}, {"crossing": "Bajakovo ", "to_cro": "do 30 min.", "from_cro": "4 h"}, {"crossing": "Macelj ", "to_cro": "1 h", "from_cro": "-"}, {"crossing": "Bregana ", "to_cro": "1 h 30 min.", "from_cro": "1 h 30 min."}, {"crossing": "Jurovski Brod ", "to_cro": "-", "from_cro": "do 30 min."}, {"crossing": "Mursko Sredi\u0161\u0107e ", "to_cro": "1 h", "from_cro": "-"}, {"crossing": "Cvetlin ", "to_cro": "1 h", "from_cro": "-"}, {"crossing": "Hum na Sutli ", "to_cro": "-", "from_cro": "do 30 min."}, {"crossing": "Lupinjak ", "to_cro": "1 h", "from_cro": "-"}], "1627786802": [{"crossing": "", "to_cro": "", "from_cro": ""}, {"crossing": "Dubo\u0161evica ", "to_cro": "1 h", "from_cro": "-"}, {"crossing": "Gori\u010dan II ", "to_cro": "do 30 min.", "from_cro": "-"}, {"crossing": "Bajakovo ", "to_cro": "do 30 min.", "from_cro": "4 h"}, {"crossing": "Macelj ", "to_cro": "1 h", "from_cro": "-"}, {"crossing": "Bregana ", "to_cro": "1 h 30 min.", "from_cro": "1 h 30 min."}, {"crossing": "Mursko Sredi\u0161\u0107e ", "to_cro": "1 h", "from_cro": "-"}, {"crossing": "Cvetlin ", "to_cro": "1 h", "from_cro": "-"}, {"crossing": "Hum na Sutli ", "to_cro": "-", "from_cro": "do 30 min."}, {"crossing": "Lupinjak ", "to_cro": "1 h", "from_cro": "-"}], "1627788602": [{"crossing": "", "to_cro": "", "from_cro": ""}, {"crossing": "Dubo\u0161evica ", "to_cro": "1 h", "from_cro": "-"}, {"crossing": "Gori\u010dan II ", "to_cro": "do 30 min.", "from_cro": "-"}, {"crossing": "Bajakovo ", "to_cro": "do 30 min.", "from_cro": "4 h"}, {"crossing": "Macelj ", "to_cro": "1 h", "from_cro": "2 h"}, {"crossing": "Bregana ", "to_cro": "1 h 30 min.", "from_cro": "1 h 30 min."}, {"crossing": "Mursko Sredi\u0161\u0107e ", "to_cro": "1 h", "from_cro": "-"}, {"crossing": "Cvetlin ", "to_cro": "1 h", "from_cro": "-"}, {"crossing": "Hum na Sutli ", "to_cro": "1 h", "from_cro": "do 30 min."}, {"crossing": "Lupinjak ", "to_cro": "1 h", "from_cro": "do 30 min."}], "1627790401": [{"crossing": "", "to_cro": "", "from_cro": ""}, {"crossing": "Dubo\u0161evica ", "to_cro": "1 h", "from_cro": "-"}, {"crossing": "Gori\u010dan II ", "to_cro": "do 30 min.", "from_cro": "-"}, {"crossing": "Bajakovo ", "to_cro": "do 30 min.", "from_cro": "4 h"}, {"crossing": "Macelj ", "to_cro": "1 h", "from_cro": "2 h"}, {"crossing": "Bregana ", "to_cro": "1 h 30 min.", "from_cro": "1 h 30 min."}, {"crossing": "Pasjak ", "to_cro": "do 30 min.", "from_cro": "-"}, {"crossing": "Jurovski Brod ", "to_cro": "1 h", "from_cro": "-"}, {"crossing": "Mursko Sredi\u0161\u0107e ", "to_cro": "1 h", "from_cro": "-"}, {"crossing": "Cvetlin ", "to_cro": "1 h", "from_cro": "-"}, {"crossing": "Hum na Sutli ", "to_cro": "1 h", "from_cro": "do 30 min."}, {"crossing": "Lupinjak ", "to_cro": "1 h", "from_cro": "do 30 min."}], "1627792202": [{"crossing": "Dubo\u0161evica ", "to_cro": "1 h", "from_cro": "-"}, {"crossing": "Gori\u010dan II ", "to_cro": "do 30 min.", "from_cro": "-"}, {"crossing": "Bajakovo ", "to_cro": "do 30 min.", "from_cro": "5 h"}, {"crossing": "Macelj ", "to_cro": "1 h", "from_cro": "2 h"}, {"crossing": "Bregana ", "to_cro": "1 h 30 min.", "from_cro": "1 h 30 min."}, {"crossing": "Pasjak ", "to_cro": "do 30 min.", "from_cro": "-"}, {"crossing": "Jurovski Brod ", "to_cro": "1 h", "from_cro": "-"}, {"crossing": "Mursko Sredi\u0161\u0107e ", "to_cro": "1 h", "from_cro": "-"}, {"crossing": "Cvetlin ", "to_cro": "1 h", "from_cro": "-"}, {"crossing": "Hum na Sutli ", "to_cro": "1 h", "from_cro": "do 30 min."}, {"crossing": "Lupinjak ", "to_cro": "1 h", "from_cro": "do 30 min."}], "1627794003": [{"crossing": "", "to_cro": "", "from_cro": ""}, {"crossing": "Maljevac ", "to_cro": "1 h", "from_cro": "-"}, {"crossing": "Gori\u010dan ", "to_cro": "do 30 min.", "from_cro": "-"}, {"crossing": "Bajakovo ", "to_cro": "do 30 min.", "from_cro": "5 h"}, {"crossing": "Macelj ", "to_cro": "1 h", "from_cro": "2 h"}, {"crossing": "Bregana ", "to_cro": "1 h 30 min.", "from_cro": "1 h 30 min."}, {"crossing": "Pasjak ", "to_cro": "1 h", "from_cro": "-"}, {"crossing": "Jurovski Brod ", "to_cro": "1 h", "from_cro": "-"}, {"crossing": "Mursko Sredi\u0161\u0107e ", "to_cro": "1 h", "from_cro": "-"}, {"crossing": "Cvetlin ", "to_cro": "1 h", "from_cro": "-"}, {"crossing": "Hum na Sutli ", "to_cro": "1 h", "from_cro": "do 30 min."}, {"crossing": "Lupinjak ", "to_cro": "1 h", "from_cro": "do 30 min."}], "1627795806": [{"crossing": "", "to_cro": "", "from_cro": ""}, {"crossing": "Maljevac ", "to_cro": "1 h", "from_cro": "-"}, {"crossing": "Dubo\u0161evica ", "to_cro": "do 30 min.", "from_cro": "-"}, {"crossing": "Gori\u010dan ", "to_cro": "do 30 min.", "from_cro": "-"}, {"crossing": "Bajakovo ", "to_cro": "do 30 min.", "from_cro": "5 h"}, {"crossing": "Tovarnik ", "to_cro": "do 30 min.", "from_cro": "1 h 30 min."}, {"crossing": "Macelj ", "to_cro": "-", "from_cro": "2 h"}, {"crossing": "Bregana ", "to_cro": "1 h 30 min.", "from_cro": "1 h 30 min."}, {"crossing": "Rupa ", "to_cro": "1 h 30 min.", "from_cro": "do 30 min."}, {"crossing": "Pasjak ", "to_cro": "1 h", "from_cro": "-"}, {"crossing": "Jurovski Brod ", "to_cro": "1 h", "from_cro": "-"}, {"crossing": "Mursko Sredi\u0161\u0107e ", "to_cro": "1 h", "from_cro": "-"}, {"crossing": "Cvetlin ", "to_cro": "1 h", "from_cro": "-"}, {"crossing": "Hum na Sutli ", "to_cro": "do 30 min.", "from_cro": "do 30 min."}, {"crossing": "Lupinjak ", "to_cro": "1 h", "from_cro": "do 30 min."}], "1627797602": [{"crossing": "", "to_cro": "", "from_cro": ""}, {"crossing": "Maljevac ", "to_cro": "1 h", "from_cro": "-"}, {"crossing": "Dubo\u0161evica ", "to_cro": "do 30 min.", "from_cro": "do 30 min."}, {"crossing": "Gori\u010dan ", "to_cro": "do 30 min.", "from_cro": "-"}, {"crossing": "Gori\u010dan II ", "to_cro": "do 30 min.", "from_cro": "-"}, {"crossing": "Bajakovo ", "to_cro": "do 30 min.", "from_cro": "5 h"}, {"crossing": "Tovarnik ", "to_cro": "do 30 min.", "from_cro": "2 h"}, {"crossing": "Macelj ", "to_cro": "-", "from_cro": "2 h"}, {"crossing": "Bregana ", "to_cro": "1 h 30 min.", "from_cro": "1 h 30 min."}, {"crossing": "Rupa ", "to_cro": "1 h 30 min.", "from_cro": "do 30 min."}, {"crossing": "Pasjak ", "to_cro": "1 h", "from_cro": "-"}, {"crossing": "Jurovski Brod ", "to_cro": "2 h", "from_cro": "-"}, {"crossing": "Cvetlin ", "to_cro": "1 h", "from_cro": "-"}, {"crossing": "Hum na Sutli ", "to_cro": "do 30 min.", "from_cro": "do 30 min."}, {"crossing": "Lupinjak ", "to_cro": "1 h", "from_cro": "do 30 min."}], "1627799402": [{"crossing": "", "to_cro": "", "from_cro": ""}, {"crossing": "Stara Gradi\u0161ka ", "to_cro": "1 h 30 min.", "from_cro": "do 30 min."}, {"crossing": "Jasenovac ", "to_cro": "do 30 min.", "from_cro": "do 30 min."}, {"crossing": "Maljevac ", "to_cro": "1 h 30 min.", "from_cro": "-"}, {"crossing": "Dubo\u0161evica ", "to_cro": "do 30 min.", "from_cro": "do 30 min."}, {"crossing": "Gori\u010dan ", "to_cro": "do 30 min.", "from_cro": "-"}, {"crossing": "Gori\u010dan II ", "to_cro": "do 30 min.", "from_cro": "-"}, {"crossing": "Bajakovo ", "to_cro": "1 h", "from_cro": "5 h"}, {"crossing": "Tovarnik ", "to_cro": "do 30 min.", "from_cro": "2 h"}, {"crossing": "Macelj ", "to_cro": "-", "from_cro": "2 h"}, {"crossing": "Bregana ", "to_cro": "1 h 30 min.", "from_cro": "1 h 30 min."}, {"crossing": "Rupa ", "to_cro": "1 h 30 min.", "from_cro": "do 30 min."}, {"crossing": "Pasjak ", "to_cro": "1 h", "from_cro": "-"}, {"crossing": "Jurovski Brod ", "to_cro": "2 h", "from_cro": "-"}, {"crossing": "Cvetlin ", "to_cro": "1 h", "from_cro": "-"}, {"crossing": "Hum na Sutli ", "to_cro": "do 30 min.", "from_cro": "do 30 min."}, {"crossing": "Lupinjak ", "to_cro": "1 h", "from_cro": "do 30 min."}, {"crossing": "Razvor ", "to_cro": "1 h", "from_cro": "-"}], "1627801203": [{"crossing": "", "to_cro": "", "from_cro": ""}, {"crossing": "Stara Gradi\u0161ka ", "to_cro": "1 h 30 min.", "from_cro": "do 30 min."}, {"crossing": "\u017dupanja ", "to_cro": "do 30 min.", "from_cro": "do 30 min."}, {"crossing": "Slavonski Brod ", "to_cro": "-", "from_cro": "do 30 min."}, {"crossing": "Jasenovac ", "to_cro": "do 30 min.", "from_cro": "do 30 min."}, {"crossing": "Maljevac ", "to_cro": "1 h 30 min.", "from_cro": "-"}, {"crossing": "Dubo\u0161evica ", "to_cro": "do 30 min.", "from_cro": "do 30 min."}, {"crossing": "Gori\u010dan ", "to_cro": "1 h", "from_cro": "-"}, {"crossing": "Gori\u010dan II ", "to_cro": "do 30 min.", "from_cro": "-"}, {"crossing": "Bajakovo ", "to_cro": "1 h", "from_cro": "5 h"}, {"crossing": "Tovarnik ", "to_cro": "do 30 min.", "from_cro": "2 h"}, {"crossing": "Macelj ", "to_cro": "do 30 min.", "from_cro": "2 h"}, {"crossing": "Bregana ", "to_cro": "1 h 30 min.", "from_cro": "1 h 30 min."}, {"crossing": "Rupa ", "to_cro": "1 h 30 min.", "from_cro": "do 30 min."}, {"crossing": "Pasjak ", "to_cro": "1 h", "from_cro": "-"}, {"crossing": "Jurovski Brod ", "to_cro": "2 h", "from_cro": "-"}, {"crossing": "Dubrava Kri\u017eovljanska ", "to_cro": "do 30 min.", "from_cro": "do 30 min."}, {"crossing": "Mursko Sredi\u0161\u0107e ", "to_cro": "1 h", "from_cro": "-"}, {"crossing": "Cvetlin ", "to_cro": "1 h", "from_cro": "-"}, {"crossing": "Hum na Sutli ", "to_cro": "do 30 min.", "from_cro": "do 30 min."}, {"crossing": "Lupinjak ", "to_cro": "1 h", "from_cro": "-"}, {"crossing": "Razvor ", "to_cro": "1 h", "from_cro": "-"}], "1627803002": [{"crossing": "", "to_cro": "", "from_cro": ""}, {"crossing": "Stara Gradi\u0161ka ", "to_cro": "2 h", "from_cro": "1 h"}, {"crossing": "\u017dupanja ", "to_cro": "do 30 min.", "from_cro": "do 30 min."}, {"crossing": "Slavonski Brod ", "to_cro": "-", "from_cro": "do 30 min."}, {"crossing": "Jasenovac ", "to_cro": "do 30 min.", "from_cro": "do 30 min."}, {"crossing": "Maljevac ", "to_cro": "1 h 30 min.", "from_cro": "-"}, {"crossing": "Dubo\u0161evica ", "to_cro": "do 30 min.", "from_cro": "do 30 min."}, {"crossing": "Gori\u010dan ", "to_cro": "1 h", "from_cro": "-"}, {"crossing": "Gori\u010dan II ", "to_cro": "do 30 min.", "from_cro": "-"}, {"crossing": "Bajakovo ", "to_cro": "1 h", "from_cro": "5 h"}, {"crossing": "Tovarnik ", "to_cro": "do 30 min.", "from_cro": "2 h"}, {"crossing": "Macelj ", "to_cro": "do 30 min.", "from_cro": "2 h"}, {"crossing": "Bregana ", "to_cro": "1 h 30 min.", "from_cro": "1 h 30 min."}, {"crossing": "Rupa ", "to_cro": "1 h", "from_cro": "1 h"}, {"crossing": "Pasjak ", "to_cro": "1 h 30 min.", "from_cro": "-"}, {"crossing": "Jurovski Brod ", "to_cro": "2 h", "from_cro": "-"}, {"crossing": "Dubrava Kri\u017eovljanska ", "to_cro": "do 30 min.", "from_cro": "do 30 min."}, {"crossing": "Mursko Sredi\u0161\u0107e ", "to_cro": "1 h", "from_cro": "-"}, {"crossing": "Cvetlin ", "to_cro": "1 h", "from_cro": "-"}, {"crossing": "Hum na Sutli ", "to_cro": "do 30 min.", "from_cro": "do 30 min."}, {"crossing": "Lupinjak ", "to_cro": "1 h", "from_cro": "-"}, {"crossing": "Razvor ", "to_cro": "1 h", "from_cro": "-"}], "1627804806": [{"crossing": "", "to_cro": "", "from_cro": ""}, {"crossing": "Stara Gradi\u0161ka ", "to_cro": "2 h", "from_cro": "1 h"}, {"crossing": "\u017dupanja ", "to_cro": "do 30 min.", "from_cro": "do 30 min."}, {"crossing": "Slavonski Brod ", "to_cro": "-", "from_cro": "do 30 min."}, {"crossing": "Jasenovac ", "to_cro": "do 30 min.", "from_cro": "do 30 min."}, {"crossing": "Maljevac ", "to_cro": "1 h 30 min.", "from_cro": "-"}, {"crossing": "Dubo\u0161evica ", "to_cro": "do 30 min.", "from_cro": "do 30 min."}, {"crossing": "Gori\u010dan ", "to_cro": "1 h", "from_cro": "-"}, {"crossing": "Gori\u010dan II ", "to_cro": "do 30 min.", "from_cro": "-"}, {"crossing": "Bajakovo ", "to_cro": "1 h", "from_cro": "5 h"}, {"crossing": "Tovarnik ", "to_cro": "do 30 min.", "from_cro": "2 h"}, {"crossing": "Macelj ", "to_cro": "1 h", "from_cro": "2 h"}, {"crossing": "Rupa ", "to_cro": "1 h", "from_cro": "1 h"}, {"crossing": "Pasjak ", "to_cro": "2 h", "from_cro": "do 30 min."}, {"crossing": "Jurovski Brod ", "to_cro": "2 h", "from_cro": "-"}, {"crossing": "Dubrava Kri\u017eovljanska ", "to_cro": "do 30 min.", "from_cro": "do 30 min."}, {"crossing": "Mursko Sredi\u0161\u0107e ", "to_cro": "1 h", "from_cro": "-"}, {"crossing": "Cvetlin ", "to_cro": "1 h", "from_cro": "-"}, {"crossing": "Hum na Sutli ", "to_cro": "do 30 min.", "from_cro": "-"}, {"crossing": "Razvor ", "to_cro": "1 h 30 min.", "from_cro": "-"}], "1627806602": [{"crossing": "", "to_cro": "", "from_cro": ""}, {"crossing": "Stara Gradi\u0161ka ", "to_cro": "-", "from_cro": "1 h"}, {"crossing": "\u017dupanja ", "to_cro": "do 30 min.", "from_cro": "do 30 min."}, {"crossing": "Jasenovac ", "to_cro": "do 30 min.", "from_cro": "do 30 min."}, {"crossing": "Maljevac ", "to_cro": "do 30 min.", "from_cro": "-"}, {"crossing": "Dubo\u0161evica ", "to_cro": "do 30 min.", "from_cro": "do 30 min."}, {"crossing": "Gori\u010dan ", "to_cro": "1 h", "from_cro": "-"}, {"crossing": "Gori\u010dan II ", "to_cro": "do 30 min.", "from_cro": "-"}, {"crossing": "Bajakovo ", "to_cro": "1 h", "from_cro": "5 h"}, {"crossing": "Tovarnik ", "to_cro": "do 30 min.", "from_cro": "3 h"}, {"crossing": "Macelj ", "to_cro": "1 h", "from_cro": "2 h"}, {"crossing": "Bregana ", "to_cro": "1 h", "from_cro": "-"}, {"crossing": "Rupa ", "to_cro": "1 h", "from_cro": "1 h"}, {"crossing": "Plovanija ", "to_cro": "do 30 min.", "from_cro": "1 h"}, {"crossing": "Pasjak ", "to_cro": "2 h", "from_cro": "do 30 min."}, {"crossing": "Jurovski Brod ", "to_cro": "2 h", "from_cro": "-"}, {"crossing": "Dubrava Kri\u017eovljanska ", "to_cro": "-", "from_cro": "do 30 min."}, {"crossing": "Mursko Sredi\u0161\u0107e ", "to_cro": "1 h", "from_cro": "-"}, {"crossing": "Cvetlin ", "to_cro": "1 h", "from_cro": "-"}, {"crossing": "Hum na Sutli ", "to_cro": "do 30 min.", "from_cro": "-"}, {"crossing": "Kamensko ", "to_cro": "1 h", "from_cro": "-"}, {"crossing": "Razvor ", "to_cro": "1 h 30 min.", "from_cro": "-"}, {"crossing": "Vinjani Gornji ", "to_cro": "1 h", "from_cro": "-"}], "1627808403": [{"crossing": "", "to_cro": "", "from_cro": ""}, {"crossing": "Stara Gradi\u0161ka ", "to_cro": "-", "from_cro": "do 30 min."}, {"crossing": "\u017dupanja ", "to_cro": "1 h", "from_cro": "do 30 min."}, {"crossing": "Jasenovac ", "to_cro": "do 30 min.", "from_cro": "do 30 min."}, {"crossing": "Maljevac ", "to_cro": "do 30 min.", "from_cro": "-"}, {"crossing": "Dubo\u0161evica ", "to_cro": "do 30 min.", "from_cro": "do 30 min."}, {"crossing": "Gori\u010dan ", "to_cro": "1 h", "from_cro": "-"}, {"crossing": "Gori\u010dan II ", "to_cro": "do 30 min.", "from_cro": "-"}, {"crossing": "Bajakovo ", "to_cro": "1 h", "from_cro": "5 h"}, {"crossing": "Tovarnik ", "to_cro": "do 30 min.", "from_cro": "3 h"}, {"crossing": "Macelj ", "to_cro": "1 h", "from_cro": "2 h"}, {"crossing": "Bregana ", "to_cro": "1 h", "from_cro": "-"}, {"crossing": "Rupa ", "to_cro": "1 h", "from_cro": "1 h"}, {"crossing": "Plovanija ", "to_cro": "do 30 min.", "from_cro": "1 h"}, {"crossing": "Pasjak ", "to_cro": "2 h", "from_cro": "do 30 min."}, {"crossing": "Jurovski Brod ", "to_cro": "2 h", "from_cro": "-"}, {"crossing": "Dubrava Kri\u017eovljanska ", "to_cro": "do 30 min.", "from_cro": "do 30 min."}, {"crossing": "Mursko Sredi\u0161\u0107e ", "to_cro": "1 h", "from_cro": "-"}, {"crossing": "Cvetlin ", "to_cro": "1 h", "from_cro": "-"}, {"crossing": "Dra\u0161e ", "to_cro": "do 30 min.", "from_cro": "-"}, {"crossing": "Hum na Sutli ", "to_cro": "do 30 min.", "from_cro": "-"}, {"crossing": "Kamensko ", "to_cro": "1 h", "from_cro": "-"}, {"crossing": "Razvor ", "to_cro": "1 h 30 min.", "from_cro": "-"}, {"crossing": "Vinjani Gornji ", "to_cro": "1 h", "from_cro": "-"}], "1627810207": [{"crossing": "", "to_cro": "", "from_cro": ""}, {"crossing": "Stara Gradi\u0161ka ", "to_cro": "-", "from_cro": "do 30 min."}, {"crossing": "\u017dupanja ", "to_cro": "1 h", "from_cro": "do 30 min."}, {"crossing": "Jasenovac ", "to_cro": "do 30 min.", "from_cro": "do 30 min."}, {"crossing": "Maljevac ", "to_cro": "do 30 min.", "from_cro": "-"}, {"crossing": "Dubo\u0161evica ", "to_cro": "do 30 min.", "from_cro": "do 30 min."}, {"crossing": "Gori\u010dan ", "to_cro": "1 h", "from_cro": "-"}, {"crossing": "Gori\u010dan II ", "to_cro": "do 30 min.", "from_cro": "-"}, {"crossing": "Bajakovo ", "to_cro": "1 h", "from_cro": "5 h"}, {"crossing": "Tovarnik ", "to_cro": "do 30 min.", "from_cro": "3 h"}, {"crossing": "Macelj ", "to_cro": "1 h", "from_cro": "2 h"}, {"crossing": "Bregana ", "to_cro": "1 h", "from_cro": "-"}, {"crossing": "Rupa ", "to_cro": "1 h", "from_cro": "1 h"}, {"crossing": "Plovanija ", "to_cro": "do 30 min.", "from_cro": "1 h"}, {"crossing": "Ka\u0161tel ", "to_cro": "1 h 30 min.", "from_cro": "1 h"}, {"crossing": "Pasjak ", "to_cro": "2 h", "from_cro": "do 30 min."}, {"crossing": "Jurovski Brod ", "to_cro": "2 h", "from_cro": "1 h"}, {"crossing": "Dubrava Kri\u017eovljanska ", "to_cro": "do 30 min.", "from_cro": "do 30 min."}, {"crossing": "Mursko Sredi\u0161\u0107e ", "to_cro": "1 h", "from_cro": "-"}, {"crossing": "Cvetlin ", "to_cro": "1 h", "from_cro": "-"}, {"crossing": "Dra\u0161e ", "to_cro": "2 h", "from_cro": "-"}, {"crossing": "Hum na Sutli ", "to_cro": "do 30 min.", "from_cro": "-"}, {"crossing": "Kamensko ", "to_cro": "1 h", "from_cro": "-"}, {"crossing": "Razvor ", "to_cro": "1 h 30 min.", "from_cro": "-"}, {"crossing": "Vinjani Gornji ", "to_cro": "1 h", "from_cro": "-"}], "1627812008": [{"crossing": "", "to_cro": "", "from_cro": ""}, {"crossing": "Stara Gradi\u0161ka ", "to_cro": "-", "from_cro": "do 30 min."}, {"crossing": "\u017dupanja ", "to_cro": "1 h", "from_cro": "do 30 min."}, {"crossing": "Slavonski Brod ", "to_cro": "do 30 min.", "from_cro": "-"}, {"crossing": "Jasenovac ", "to_cro": "do 30 min.", "from_cro": "do 30 min."}, {"crossing": "Maljevac ", "to_cro": "do 30 min.", "from_cro": "-"}, {"crossing": "Gori\u010dan ", "to_cro": "1 h", "from_cro": "-"}, {"crossing": "Bajakovo ", "to_cro": "1 h", "from_cro": "5 h"}, {"crossing": "Tovarnik ", "to_cro": "-", "from_cro": "3 h"}, {"crossing": "Macelj ", "to_cro": "1 h", "from_cro": "2 h"}, {"crossing": "Bregana ", "to_cro": "1 h", "from_cro": "-"}, {"crossing": "Rupa ", "to_cro": "3 h", "from_cro": "2 h"}, {"crossing": "Plovanija ", "to_cro": "do 30 min.", "from_cro": "1 h"}, {"crossing": "Ka\u0161tel ", "to_cro": "1 h 30 min.", "from_cro": "1 h"}, {"crossing": "Pasjak ", "to_cro": "2 h", "from_cro": "do 30 min."}, {"crossing": "Jurovski Brod ", "to_cro": "-", "from_cro": "1 h"}, {"crossing": "Mursko Sredi\u0161\u0107e ", "to_cro": "1 h", "from_cro": "-"}, {"crossing": "Dra\u0161e ", "to_cro": "2 h", "from_cro": "-"}, {"crossing": "Kamensko ", "to_cro": "1 h", "from_cro": "-"}, {"crossing": "Vinjani Gornji ", "to_cro": "1 h", "from_cro": "-"}], "1627813802": [{"crossing": "", "to_cro": "", "from_cro": ""}, {"crossing": "Stara Gradi\u0161ka ", "to_cro": "-", "from_cro": "do 30 min."}, {"crossing": "\u017dupanja ", "to_cro": "1 h", "from_cro": "do 30 min."}, {"crossing": "Slavonski Brod ", "to_cro": "do 30 min.", "from_cro": "-"}, {"crossing": "Jasenovac ", "to_cro": "do 30 min.", "from_cro": "do 30 min."}, {"crossing": "Maljevac ", "to_cro": "do 30 min.", "from_cro": "-"}, {"crossing": "Dubo\u0161evica ", "to_cro": "1 h", "from_cro": "-"}, {"crossing": "Gori\u010dan ", "to_cro": "do 30 min.", "from_cro": "-"}, {"crossing": "Gori\u010dan II ", "to_cro": "do 30 min.", "from_cro": "-"}, {"crossing": "Bajakovo ", "to_cro": "1 h", "from_cro": "5 h"}, {"crossing": "Tovarnik ", "to_cro": "-", "from_cro": "3 h"}, {"crossing": "Macelj ", "to_cro": "1 h", "from_cro": "2 h"}, {"crossing": "Bregana ", "to_cro": "1 h", "from_cro": "-"}, {"crossing": "Rupa ", "to_cro": "3 h", "from_cro": "2 h"}, {"crossing": "Plovanija ", "to_cro": "do 30 min.", "from_cro": "1 h"}, {"crossing": "Ka\u0161tel ", "to_cro": "1 h 30 min.", "from_cro": "1 h 30 min."}, {"crossing": "Pasjak ", "to_cro": "2 h", "from_cro": "do 30 min."}, {"crossing": "Jurovski Brod ", "to_cro": "-", "from_cro": "1 h"}, {"crossing": "Mursko Sredi\u0161\u0107e ", "to_cro": "1 h", "from_cro": "-"}, {"crossing": "Dra\u0161e ", "to_cro": "2 h", "from_cro": "-"}, {"crossing": "Dvor ", "to_cro": "1 h", "from_cro": "-"}, {"crossing": "Kamensko ", "to_cro": "1 h", "from_cro": "-"}, {"crossing": "Vinjani Gornji ", "to_cro": "1 h", "from_cro": "-"}], "1627815602": [{"crossing": "", "to_cro": "", "from_cro": ""}, {"crossing": "Slavonski Brod ", "to_cro": "do 30 min.", "from_cro": "-"}, {"crossing": "Dubo\u0161evica ", "to_cro": "1 h", "from_cro": "-"}, {"crossing": "Gori\u010dan II ", "to_cro": "do 30 min.", "from_cro": "-"}, {"crossing": "Tovarnik ", "to_cro": "-", "from_cro": "3 h"}, {"crossing": "Macelj ", "to_cro": "1 h", "from_cro": "2 h"}, {"crossing": "Bregana ", "to_cro": "1 h", "from_cro": "-"}, {"crossing": "Rupa ", "to_cro": "2 h", "from_cro": "1 h"}, {"crossing": "Plovanija ", "to_cro": "do 30 min.", "from_cro": "1 h"}, {"crossing": "Ka\u0161tel ", "to_cro": "1 h 30 min.", "from_cro": "1 h 30 min."}, {"crossing": "Po\u017eane ", "to_cro": "do 30 min.", "from_cro": "1 h"}, {"crossing": "Pasjak ", "to_cro": "2 h", "from_cro": "do 30 min."}, {"crossing": "Jurovski Brod ", "to_cro": "-", "from_cro": "1 h"}, {"crossing": "Dubrava Kri\u017eovljanska ", "to_cro": "-", "from_cro": "do 30 min."}, {"crossing": "Dra\u0161e ", "to_cro": "2 h", "from_cro": "-"}, {"crossing": "Dvor ", "to_cro": "1 h", "from_cro": "-"}, {"crossing": "Kamensko ", "to_cro": "1 h", "from_cro": "-"}, {"crossing": "Otok Virje ", "to_cro": "-", "from_cro": "do 30 min."}, {"crossing": "Slavonski \u0160amac ", "to_cro": "1 h", "from_cro": "-"}, {"crossing": "Vinjani Gornji ", "to_cro": "1 h", "from_cro": "-"}], "1627817410": [{"crossing": "", "to_cro": "", "from_cro": ""}, {"crossing": "Stara Gradi\u0161ka ", "to_cro": "1 h", "from_cro": "1 h"}, {"crossing": "Dubo\u0161evica ", "to_cro": "1 h", "from_cro": "do 30 min."}, {"crossing": "Gori\u010dan ", "to_cro": "do 30 min.", "from_cro": "-"}, {"crossing": "Gori\u010dan II ", "to_cro": "do 30 min.", "from_cro": "-"}, {"crossing": "Tovarnik ", "to_cro": "do 30 min.", "from_cro": "3 h"}, {"crossing": "Macelj ", "to_cro": "do 30 min.", "from_cro": "2 h"}, {"crossing": "Bregana ", "to_cro": "1 h", "from_cro": "-"}, {"crossing": "Rupa ", "to_cro": "2 h", "from_cro": "1 h"}, {"crossing": "Plovanija ", "to_cro": "do 30 min.", "from_cro": "1 h 30 min."}, {"crossing": "Ka\u0161tel ", "to_cro": "1 h 30 min.", "from_cro": "1 h 30 min."}, {"crossing": "Po\u017eane ", "to_cro": "do 30 min.", "from_cro": "1 h"}, {"crossing": "Pasjak ", "to_cro": "2 h", "from_cro": "do 30 min."}, {"crossing": "Jurovski Brod ", "to_cro": "-", "from_cro": "1 h"}, {"crossing": "Dra\u0161e ", "to_cro": "do 30 min.", "from_cro": "-"}, {"crossing": "Dvor ", "to_cro": "1 h", "from_cro": "-"}, {"crossing": "Kamensko ", "to_cro": "1 h", "from_cro": "-"}, {"crossing": "Lupinjak ", "to_cro": "1 h 30 min.", "from_cro": "do 30 min."}, {"crossing": "Otok Virje ", "to_cro": "-", "from_cro": "do 30 min."}, {"crossing": "Slavonski \u0160amac ", "to_cro": "1 h", "from_cro": "-"}, {"crossing": "Vinjani Gornji ", "to_cro": "1 h", "from_cro": "-"}], "1627819202": [{"crossing": "", "to_cro": "", "from_cro": ""}, {"crossing": "Stara Gradi\u0161ka ", "to_cro": "1 h", "from_cro": "1 h"}, {"crossing": "Dubo\u0161evica ", "to_cro": "1 h", "from_cro": "do 30 min."}, {"crossing": "Gori\u010dan ", "to_cro": "do 30 min.", "from_cro": "-"}, {"crossing": "Gori\u010dan II ", "to_cro": "do 30 min.", "from_cro": "-"}, {"crossing": "Tovarnik ", "to_cro": "do 30 min.", "from_cro": "3 h"}, {"crossing": "Macelj ", "to_cro": "do 30 min.", "from_cro": "2 h"}, {"crossing": "Bregana ", "to_cro": "1 h", "from_cro": "-"}, {"crossing": "Rupa ", "to_cro": "2 h", "from_cro": "1 h"}, {"crossing": "Plovanija ", "to_cro": "do 30 min.", "from_cro": "1 h 30 min."}, {"crossing": "Ka\u0161tel ", "to_cro": "1 h", "from_cro": "1 h 30 min."}, {"crossing": "Po\u017eane ", "to_cro": "do 30 min.", "from_cro": "1 h"}, {"crossing": "Jurovski Brod ", "to_cro": "-", "from_cro": "1 h"}, {"crossing": "Mursko Sredi\u0161\u0107e ", "to_cro": "1 h", "from_cro": "-"}, {"crossing": "Ar\u017eano ", "to_cro": "1 h", "from_cro": "do 30 min."}, {"crossing": "Dra\u0161e ", "to_cro": "do 30 min.", "from_cro": "-"}, {"crossing": "Dvor ", "to_cro": "1 h", "from_cro": "-"}, {"crossing": "Kamensko ", "to_cro": "1 h", "from_cro": "-"}, {"crossing": "Lupinjak ", "to_cro": "1 h 30 min.", "from_cro": "do 30 min."}, {"crossing": "Otok Virje ", "to_cro": "-", "from_cro": "do 30 min."}, {"crossing": "Slavonski \u0160amac ", "to_cro": "1 h", "from_cro": "-"}, {"crossing": "Vinjani Gornji ", "to_cro": "1 h", "from_cro": "-"}], "1627821003": [{"crossing": "", "to_cro": "", "from_cro": "", "coordinate_x": 19.09052, "coordinate_y": 45.0486336}, {"crossing": "Stara Gradi\u0161ka ", "to_cro": "1 h 30 min.", "from_cro": "1 h 30 min.", "coordinate_x": 17.246347, "coordinate_y": 45.151164}, {"crossing": "\u017dupanja ", "to_cro": "1 h", "from_cro": "do 30 min.", "coordinate_x": 18.70347, "coordinate_y": 45.046352}, {"crossing": "Zaton Doli ", "to_cro": "do 30 min.", "from_cro": "-", "coordinate_x": 17.651577, "coordinate_y": 42.889412}, {"crossing": "Dubo\u0161evica ", "to_cro": "1 h", "from_cro": "do 30 min.", "coordinate_x": 18.660851, "coordinate_y": 45.894576}, {"crossing": "Gori\u010dan ", "to_cro": "do 30 min.", "from_cro": "-", "coordinate_x": 16.713227, "coordinate_y": 46.412283}, {"crossing": "Gori\u010dan II ", "to_cro": "do 30 min.", "from_cro": "-", "coordinate_x": 16.689988, "coordinate_y": 46.418129}, {"crossing": "Tovarnik ", "to_cro": "do 30 min.", "from_cro": "3 h", "coordinate_x": 19.170414, "coordinate_y": 45.157234}, {"crossing": "Macelj ", "to_cro": "do 30 min.", "from_cro": "2 h", "coordinate_x": 15.87, "coordinate_y": 46.27}, {"crossing": "Bregana ", "to_cro": "1 h", "from_cro": "-", "coordinate_x": 15.6984248757, "coordinate_y": 45.8426998919}, {"crossing": "Rupa ", "to_cro": "2 h", "from_cro": "1 h", "coordinate_x": 14.28, "coordinate_y": 45.49}, {"crossing": "Plovanija ", "to_cro": "do 30 min.", "from_cro": "1 h 30 min.", "coordinate_x": 13.621709, "coordinate_y": 45.463233}, {"crossing": "Ka\u0161tel ", "to_cro": "do 30 min.", "from_cro": "1 h 30 min.", "coordinate_x": 13.6504, "coordinate_y": 45.453642}, {"crossing": "Po\u017eane ", "to_cro": "do 30 min.", "from_cro": "1 h", "coordinate_x": 13.908463, "coordinate_y": 45.457544}, {"crossing": "Jurovski Brod ", "to_cro": "-", "from_cro": "1 h", "coordinate_x": 15.321793, "coordinate_y": 45.633058}, {"crossing": "Mursko Sredi\u0161\u0107e ", "to_cro": "1 h", "from_cro": "-", "coordinate_x": 16.44026, "coordinate_y": 46.514144}, {"crossing": "Ar\u017eano ", "to_cro": "1 h", "from_cro": "do 30 min.", "coordinate_x": 16.99, "coordinate_y": 43.61}, {"crossing": "Dra\u0161e ", "to_cro": "do 30 min.", "from_cro": "-", "coordinate_x": 15.711468, "coordinate_y": 46.004525}, {"crossing": "Dvor ", "to_cro": "1 h", "from_cro": "-", "coordinate_x": 16.371599, "coordinate_y": 45.05023}, {"crossing": "Kamensko ", "to_cro": "1 h", "from_cro": "-", "coordinate_x": 16.98, "coordinate_y": 43.61}, {"crossing": "Lupinjak ", "to_cro": "1 h 30 min.", "from_cro": "do 30 min.", "coordinate_x": 15.76882, "coordinate_y": 46.208851}, {"crossing": "Otok Virje ", "to_cro": "-", "from_cro": "do 30 min.", "coordinate_x": 16.153232, "coordinate_y": 46.401521}, {"crossing": "Slavonski \u0160amac ", "to_cro": "1 h", "from_cro": "-", "coordinate_x": 18.496752, "coordinate_y": 45.066492}, {"crossing": "Vinjani Gornji ", "to_cro": "1 h", "from_cro": "-", "coordinate_x": 17.285227, "coordinate_y": 43.460191}], "1627822802": [{"crossing": "", "to_cro": "", "from_cro": "", "coordinate_x": 19.09052, "coordinate_y": 45.0486336}, {"crossing": "Stara Gradi\u0161ka ", "to_cro": "1 h 30 min.", "from_cro": "1 h 30 min.", "coordinate_x": 17.246347, "coordinate_y": 45.151164}, {"crossing": "\u017dupanja ", "to_cro": "1 h", "from_cro": "do 30 min.", "coordinate_x": 18.70347, "coordinate_y": 45.046352}, {"crossing": "Zaton Doli ", "to_cro": "do 30 min.", "from_cro": "-", "coordinate_x": 17.651577, "coordinate_y": 42.889412}, {"crossing": "Dubo\u0161evica ", "to_cro": "1 h", "from_cro": "do 30 min.", "coordinate_x": 18.660851, "coordinate_y": 45.894576}, {"crossing": "Gori\u010dan ", "to_cro": "do 30 min.", "from_cro": "-", "coordinate_x": 16.713227, "coordinate_y": 46.412283}, {"crossing": "Gori\u010dan II ", "to_cro": "do 30 min.", "from_cro": "-", "coordinate_x": 16.689988, "coordinate_y": 46.418129}, {"crossing": "Tovarnik ", "to_cro": "do 30 min.", "from_cro": "3 h", "coordinate_x": 19.170414, "coordinate_y": 45.157234}, {"crossing": "Macelj ", "to_cro": "do 30 min.", "from_cro": "2 h", "coordinate_x": 15.87, "coordinate_y": 46.27}, {"crossing": "Rupa ", "to_cro": "2 h", "from_cro": "1 h", "coordinate_x": 14.28, "coordinate_y": 45.49}, {"crossing": "Plovanija ", "to_cro": "do 30 min.", "from_cro": "1 h 30 min.", "coordinate_x": 13.621709, "coordinate_y": 45.463233}, {"crossing": "Ka\u0161tel ", "to_cro": "do 30 min.", "from_cro": "1 h 30 min.", "coordinate_x": 13.6504, "coordinate_y": 45.453642}, {"crossing": "Po\u017eane ", "to_cro": "do 30 min.", "from_cro": "1 h", "coordinate_x": 13.908463, "coordinate_y": 45.457544}, {"crossing": "Jurovski Brod ", "to_cro": "1 h", "from_cro": "1 h", "coordinate_x": 15.321793, "coordinate_y": 45.633058}, {"crossing": "Mursko Sredi\u0161\u0107e ", "to_cro": "1 h", "from_cro": "-", "coordinate_x": 16.44026, "coordinate_y": 46.514144}, {"crossing": "Ar\u017eano ", "to_cro": "1 h", "from_cro": "do 30 min.", "coordinate_x": 16.99, "coordinate_y": 43.61}, {"crossing": "Dvor ", "to_cro": "1 h", "from_cro": "-", "coordinate_x": 16.371599, "coordinate_y": 45.05023}, {"crossing": "Kamensko ", "to_cro": "1 h", "from_cro": "-", "coordinate_x": 16.98, "coordinate_y": 43.61}, {"crossing": "Lupinjak ", "to_cro": "-", "from_cro": "do 30 min.", "coordinate_x": 15.76882, "coordinate_y": 46.208851}, {"crossing": "Otok Virje ", "to_cro": "-", "from_cro": "do 30 min.", "coordinate_x": 16.153232, "coordinate_y": 46.401521}, {"crossing": "Slavonski \u0160amac ", "to_cro": "1 h", "from_cro": "-", "coordinate_x": 18.496752, "coordinate_y": 45.066492}]}